<?xml version="1.0" encoding="UTF-8"?>

<!--El documento es válido-->
<libreria>

<libro categoria="cocina">
  <titulo> Titanica </titulo>
  <autor>  Eva Garcia Saenz de Urturi </autor>
  <editorial> Editorial planeta </editorial>
</libro>

<libro categoria="novela">
  <titulo> Linea de fuego </titulo>
 <autor> Arturo Perez-Reverte </autor>
 <editorial> Alfaguara </editorial>
</libro>

<libro categoria="programacion">
<titulo > Un oceano para llegar a ti </titulo>
<autor> Sandra Barnera </autor>
<editorial> Editorial planeta </editorial>
</libro>

<libro categoria="programacion">
  <titulo> Las tinieblas y el alba </titulo>
  <autor> Ken Follett </autor>
  <editorial> Plazas y Janes </editorial>
</libro>

</libreria>
